LICENSE.txt
MANIFEST.in
README.txt
setup.py
pcart_novaposhta/__init__.py
pcart_novaposhta/admin.py
pcart_novaposhta/apps.py
pcart_novaposhta/models.py
pcart_novaposhta/shipping.py
pcart_novaposhta/utils.py
pcart_novaposhta.egg-info/PKG-INFO
pcart_novaposhta.egg-info/SOURCES.txt
pcart_novaposhta.egg-info/dependency_links.txt
pcart_novaposhta.egg-info/not-zip-safe
pcart_novaposhta.egg-info/requires.txt
pcart_novaposhta.egg-info/top_level.txt
pcart_novaposhta/locale/ru/LC_MESSAGES/django.mo
pcart_novaposhta/locale/ru/LC_MESSAGES/django.po
pcart_novaposhta/locale/uk/LC_MESSAGES/django.mo
pcart_novaposhta/locale/uk/LC_MESSAGES/django.po
pcart_novaposhta/migrations/0001_initial.py
pcart_novaposhta/migrations/0002_auto_20170306_2143.py
pcart_novaposhta/migrations/0003_auto_20170306_2145.py
pcart_novaposhta/migrations/0004_auto_20170306_2218.py
pcart_novaposhta/migrations/__init__.py
pcart_novaposhta/templates/admin/novaposhta/shipping_preview.html
pcart_novaposhta/templates/admin/novaposhta/shipping_preview.txt
pcart_novaposhta/templates/novaposhta/info_block.html